<?xml version="1.0" encoding="UTF-8"?>
<objects serializationModel="Studio.02.02.00">
	<object class="AudioFile" id="{07dbf63f-4801-4e6b-98ee-eb949cce0e9f}">
		<property name="assetPath">
			<value>BowReleaseSoundsFolder/Bow_Release_Sound_5.wav</value>
		</property>
		<property name="frequencyInKHz">
			<value>44.0999985</value>
		</property>
		<property name="channelCount">
			<value>2</value>
		</property>
		<property name="length">
			<value>0.81249433106575963</value>
		</property>
		<relationship name="masterAssetFolder">
			<destination>{6989cba3-5e26-4e07-9aa2-d090ed9f0eec}</destination>
		</relationship>
	</object>
</objects>
